contactus/__init__.py
contactus/forms.py
contactus/models.py
contactus/smoke.py
contactus/urls.py
contactus/views.py
contactus/templates/contactus/contact.html
contactus/templates/contactus/contact_notification_email.txt
contactus/templates/contactus/contact_success.html
contactus/tests/__init__.py
contactus/tests/test_forms.py
contactus/tests/test_views.py
django_contact_us-1.1.0.dist-info/METADATA
django_contact_us-1.1.0.dist-info/WHEEL
django_contact_us-1.1.0.dist-info/top_level.txt
django_contact_us-1.1.0.dist-info/RECORD
