Metadata-Version: 2.1
Name: django-contact-us
Version: 1.1.0
Summary: Django Contact Us Form
Home-page: https://github.com/ccnmtl/django-contact-us
Author: Susan Dreher
Author-email: sdreher@columbia.edu
License: BSD
Platform: any
Requires-Dist: Django
